{
    "menuItems": [
    {
        "name": "Tostadas de atun",
        "slug": "tuna_tostada",
        "category": "AL CRUDO",
        "image": "",
        "id": 1,
        "price": "16",
        "description": "Fried wonton with chipotle mayonnaise and fresh tuna",
        "ingredients": [
            {
                "name": "cheese",
                "slug": "cheese",
                "image": "",
                "description":"Chiwawah Cheese melted"
            }
        ]
    },
    {
        "name": "Shrimp Aguachile",
        "slug": "",
        "category": "",
        "image": "",
        "id": 2,
        "price": "15",
        "description": "Lemon pickled shrimp with aguachile sauce",
        "ingredients": [
            {
                "name": "",
                "slug": "",
                "image": "",
                "description":""
            }
        ] 
    },
    {
        "name": "Torre de Marisco",
        "slug": "",
        "category": "",
        "image": "",
        "id": 3,
        "price": "20",
        "description": "Seafood mix Tower with black seafood sauce",
        "ingredients": [
            {
                "name": "",
                "slug": "",
                "image": "",
                "description":""
            }
        ] 
    },
    {
        "name": "Oysters",
        "slug": "",
        "category": "appertiser",
        "image": "",
        "id": 4,
        "price": "1/2 dozen 12 Dozen 23",
        "description": "Fresh oysters with mineronette sauce",
        "ingredients": [
            {
                "name": "",
                "slug": "",
                "image": "",
                "description":""
            }
        ]
        },
        {
            "name": "Tartare Salmon",
            "slug": "",
            "category": "appertiser",
            "image": "",
            "id": 5,
            "price": "15",
            "description": "Salmon with chipotle passion fruit sauce and fried jalapeno, and avocado",
            "ingredients": [
                {
                    "name": "",
                    "slug": "",
                    "image": "",
                    "description":""
                }
            ]
        },
        {
            "name": "Sashimi Tuna",
            "slug": "",
            "category": "appertiser",
            "image": "",
            "id": 6,
            "price": "24",
            "description": "Capers, fried leek and truffle and black habanero",
            "ingredients": [
                {
                    "name": "",
                    "slug": "",
                    "image": "",
                    "description":""
                }
            ]
        }
             

    ]
}